{"sessionid":"26399036_0","advertisersid":0,"adorderid":0,"adcreativeid":0,"adplatformproviderid":100018,"sdkversion":"0","adplatformkey":"62150599CFC74B48A1D8A086EA70A232","putinmodeltype":1,"requestmode":1,"adprice":0.0,"adppprice":0.0,"requestdate":"2016-10-01 06:19:19","ip":"125.67.14.38","appid":"1","appname":"爱奇艺","uuid":"4df2d8d77880e42510b635c2a492b7c7","device":"未知","client":1,"osversion":"未知","density":"","pw":0,"ph":0,"long":"0","lat":"0","ispid":4,"ispname":"未知","networkmannerid":3,"networkmannername":"Wifi","iseffective":0,"isbilling":0,"adspacetype":9,"adspacetypename":"视频暂停悬浮","devicetype":1,"processnode":2,"apptype":4,"district":"未知","paymode":1,"isbid":0,"bidprice":0.0,"winprice":0.0,"iswin":0,"cur":"0","rate":0.0,"cnywinprice":0.0,"imei":"","mac":"","idfa":"","openudid":"","androidid":"7cd4deb847adce16","rtbprovince":"","rtbcity":"","rtbdistrict":"","rtbstreet":"","storeurl":"","realip":"","isqualityapp":0,"bidfloor":400.0,"aw":600,"ah":500,"imeimd5":"4df2d8d77880e42510b635c2a492b7c7","macmd5":"","idfamd5":"","openudidmd5":"","androididmd5":"","imeisha1":"","macsha1":"","idfasha1":"","openudidsha1":"","androididsha1":"","uuidunknow":"","userid":"4df2d8d77880e42510b635c2a492b7c7","iptype":1,"initbidprice":0.0,"adpayment":0.0,"agentrate":0.0,"lomarkrate":0.0,"adxrate":0.0,"title":"","keywords":"怀旧|复仇|巨星电影|动作|友谊|类型|刘嘉玲系列|当代|类型|热门电影|华语|喜剧片|功夫|类型|犯罪片|院线|刘德华系列|喜剧|动作片|王晶系列|地区|国语|","tagid":"1000000000410","callbackdate":"2016-10-01 06:19:19","channelid":"1","mediatype":2}
{"sessionid":"","advertisersid":0,"adorderid":0,"adcreativeid":0,"adplatformproviderid":13,"sdkversion":"未知","adplatformkey":"0b0c1c5523aa40c3a5dcde4402947693","putinmodeltype":0,"requestmode":1,"adprice":0.0,"adppprice":5.0,"requestdate":"2016-10-01 06:19:19","ip":"183.223.242.0","appid":"9cfa151718bde7a960090706cf7d6274d9623ec1","appname":"其他","uuid":"200729720072976","device":"未知","client":2,"osversion":"2.3","density":"1","pw":0,"ph":0,"long":"","lat":"","ispid":3,"ispname":"电信","networkmannerid":2,"networkmannername":"3G","iseffective":0,"isbilling":0,"adspacetype":2,"adspacetypename":"插屏","devicetype":1,"processnode":2,"apptype":3,"district":"未知","paymode":1,"isbid":0,"bidprice":0.0,"winprice":0.0,"iswin":0,"cur":"0","rate":0.0,"cnywinprice":0.0,"imei":"","mac":"","idfa":"","openudid":"","androidid":"","rtbprovince":"","rtbcity":"","rtbdistrict":"","rtbstreet":"","storeurl":"","realip":"183.223.242.0","isqualityapp":0,"bidfloor":0.0,"aw":400,"ah":300,"imeimd5":"","macmd5":"","idfamd5":"","openudidmd5":"","androididmd5":"","imeisha1":"","macsha1":"","idfasha1":"","openudidsha1":"","androididsha1":"","uuidunknow":"","userid":"","iptype":1,"initbidprice":0.0,"adpayment":0.0,"agentrate":0.0,"lomarkrate":0.0,"adxrate":0.0,"title":"","keywords":"","tagid":"","callbackdate":"2016-10-01 06:19:19","channelid":"","mediatype":1}
