{"sessionid":"26085326_0","advertisersid":0,"adorderid":0,"adcreativeid":0,"adplatformproviderid":100018,"sdkversion":"0","adplatformkey":"62150599CFC74B48A1D8A086EA70A232","putinmodeltype":1,"requestmode":1,"adprice":0.0,"adppprice":0.0,"requestdate":"2016-10-01 06:19:17","ip":"139.200.216.243","appid":"1","appname":"爱奇艺","uuid":"99000658265408","device":"未知","client":1,"osversion":"未知","density":"","pw":0,"ph":0,"long":"0","lat":"0","ispid":4,"ispname":"未知","networkmannerid":3,"networkmannername":"Wifi","iseffective":0,"isbilling":0,"adspacetype":9,"adspacetypename":"视频暂停悬浮","devicetype":1,"processnode":2,"apptype":4,"district":"未知","paymode":1,"isbid":0,"bidprice":0.0,"winprice":0.0,"iswin":0,"cur":"0","rate":0.0,"cnywinprice":0.0,"imei":"","mac":"","idfa":"","openudid":"","androidid":"219aadfbd67a2cc8","rtbprovince":"","rtbcity":"","rtbdistrict":"","rtbstreet":"","storeurl":"","realip":"","isqualityapp":0,"bidfloor":400.0,"aw":600,"ah":500,"imeimd5":"99000658265408","macmd5":"","idfamd5":"","openudidmd5":"","androididmd5":"","imeisha1":"","macsha1":"","idfasha1":"","openudidsha1":"","androididsha1":"","uuidunknow":"","userid":"99000658265408","iptype":1,"initbidprice":0.0,"adpayment":0.0,"agentrate":0.0,"lomarkrate":0.0,"adxrate":0.0,"title":"","keywords":"言情剧|类型|国语|离婚|地区|剧情|剧情|生活|浪漫|配音语种|最新更新|家庭剧|内地剧场|内地|剧情|婚姻|爱情|华语剧场","tagid":"1000000000410","callbackdate":"2016-10-01 06:19:17","channelid":"2","mediatype":2}
{"sessionid":"","advertisersid":0,"adorderid":0,"adcreativeid":0,"adplatformproviderid":13,"sdkversion":"未知","adplatformkey":"0b0c1c5523aa40c3a5dcde4402947693","putinmodeltype":0,"requestmode":1,"adprice":0.0,"adppprice":5.0,"requestdate":"2016-10-01 06:19:17","ip":"221.10.135.0","appid":"c1eb4036baa6c944b7cc21407acdcf9e8d9b99b1","appname":"其他","uuid":"448070844807084","device":"未知","client":2,"osversion":"2.5","density":"1","pw":0,"ph":0,"long":"","lat":"","ispid":1,"ispname":"移动","networkmannerid":5,"networkmannername":"4G","iseffective":0,"isbilling":0,"adspacetype":2,"adspacetypename":"插屏","devicetype":1,"processnode":2,"apptype":4,"district":"未知","paymode":1,"isbid":0,"bidprice":0.0,"winprice":0.0,"iswin":0,"cur":"0","rate":0.0,"cnywinprice":0.0,"imei":"","mac":"","idfa":"","openudid":"","androidid":"","rtbprovince":"","rtbcity":"","rtbdistrict":"","rtbstreet":"","storeurl":"","realip":"221.10.135.0","isqualityapp":0,"bidfloor":0.0,"aw":400,"ah":250,"imeimd5":"","macmd5":"","idfamd5":"","openudidmd5":"","androididmd5":"","imeisha1":"","macsha1":"","idfasha1":"","openudidsha1":"","androididsha1":"","uuidunknow":"","userid":"","iptype":1,"initbidprice":0.0,"adpayment":0.0,"agentrate":0.0,"lomarkrate":0.0,"adxrate":0.0,"title":"","keywords":"","tagid":"","callbackdate":"2016-10-01 06:19:17","channelid":"","mediatype":1}
{"sessionid":"","advertisersid":0,"adorderid":0,"adcreativeid":0,"adplatformproviderid":13,"sdkversion":"未知","adplatformkey":"0b0c1c5523aa40c3a5dcde4402947693","putinmodeltype":0,"requestmode":1,"adprice":0.0,"adppprice":3.0,"requestdate":"2016-10-01 06:19:17","ip":"221.10.135.0","appid":"c1eb4036baa6c944b7cc21407acdcf9e8d9b99b1","appname":"其他","uuid":"397994239799427","device":"未知","client":1,"osversion":"2.7","density":"1","pw":0,"ph":0,"long":"","lat":"","ispid":1,"ispname":"移动","networkmannerid":1,"networkmannername":"2G","iseffective":0,"isbilling":0,"adspacetype":1,"adspacetypename":"banner","devicetype":1,"processnode":2,"apptype":4,"district":"未知","paymode":1,"isbid":0,"bidprice":0.0,"winprice":0.0,"iswin":0,"cur":"0","rate":0.0,"cnywinprice":0.0,"imei":"","mac":"","idfa":"","openudid":"","androidid":"","rtbprovince":"","rtbcity":"","rtbdistrict":"","rtbstreet":"","storeurl":"","realip":"221.10.135.0","isqualityapp":0,"bidfloor":0.0,"aw":640,"ah":100,"imeimd5":"","macmd5":"","idfamd5":"","openudidmd5":"","androididmd5":"","imeisha1":"","macsha1":"","idfasha1":"","openudidsha1":"","androididsha1":"","uuidunknow":"","userid":"","iptype":1,"initbidprice":0.0,"adpayment":0.0,"agentrate":0.0,"lomarkrate":0.0,"adxrate":0.0,"title":"","keywords":"","tagid":"","callbackdate":"2016-10-01 06:19:17","channelid":"","mediatype":1}
{"sessionid":"24981964_0","advertisersid":0,"adorderid":0,"adcreativeid":0,"adplatformproviderid":100018,"sdkversion":"0","adplatformkey":"62150599CFC74B48A1D8A086EA70A232","putinmodeltype":1,"requestmode":1,"adprice":0.0,"adppprice":0.0,"requestdate":"2016-10-01 06:19:19","ip":"218.89.51.240","appid":"1","appname":"爱奇艺","uuid":"B7F6EE8C-6E12-43EB-8BCA-C3A76B192380","device":"未知","client":2,"osversion":"未知","density":"","pw":0,"ph":0,"long":"0","lat":"0","ispid":4,"ispname":"未知","networkmannerid":3,"networkmannername":"Wifi","iseffective":0,"isbilling":0,"adspacetype":9,"adspacetypename":"视频暂停悬浮","devicetype":1,"processnode":2,"apptype":4,"district":"未知","paymode":1,"isbid":0,"bidprice":0.0,"winprice":0.0,"iswin":0,"cur":"0","rate":0.0,"cnywinprice":0.0,"imei":"","mac":"","idfa":"B7F6EE8C-6E12-43EB-8BCA-C3A76B192380","openudid":"","androidid":"","rtbprovince":"","rtbcity":"","rtbdistrict":"","rtbstreet":"","storeurl":"","realip":"","isqualityapp":0,"bidfloor":400.0,"aw":600,"ah":500,"imeimd5":"","macmd5":"","idfamd5":"","openudidmd5":"","androididmd5":"","imeisha1":"","macsha1":"","idfasha1":"","openudidsha1":"","androididsha1":"","uuidunknow":"","userid":"B7F6EE8C-6E12-43EB-8BCA-C3A76B192380","iptype":1,"initbidprice":0.0,"adpayment":0.0,"agentrate":0.0,"lomarkrate":0.0,"adxrate":0.0,"title":"","keywords":"类型|生活|国语|内地剧场|内地|家庭剧|配音语种|言情剧|青春剧|剧情|地区|剧情|爱情|剧情","tagid":"1000000000410","callbackdate":"2016-10-01 06:19:19","channelid":"2","mediatype":2}
{"sessionid":"","advertisersid":0,"adorderid":0,"adcreativeid":0,"adplatformproviderid":13,"sdkversion":"未知","adplatformkey":"0b0c1c5523aa40c3a5dcde4402947693","putinmodeltype":0,"requestmode":1,"adprice":0.0,"adppprice":3.0,"requestdate":"2016-10-01 06:19:19","ip":"221.10.135.0","appid":"db55we6weg4hj4","appname":"其他","uuid":"796502079650209","device":"未知","client":1,"osversion":"2.5","density":"1","pw":0,"ph":0,"long":"","lat":"","ispid":3,"ispname":"电信","networkmannerid":5,"networkmannername":"4G","iseffective":0,"isbilling":0,"adspacetype":1,"adspacetypename":"banner","devicetype":1,"processnode":2,"apptype":4,"district":"未知","paymode":1,"isbid":0,"bidprice":0.0,"winprice":0.0,"iswin":0,"cur":"0","rate":0.0,"cnywinprice":0.0,"imei":"","mac":"","idfa":"","openudid":"","androidid":"","rtbprovince":"","rtbcity":"","rtbdistrict":"","rtbstreet":"","storeurl":"","realip":"221.10.135.0","isqualityapp":0,"bidfloor":0.0,"aw":640,"ah":100,"imeimd5":"","macmd5":"","idfamd5":"","openudidmd5":"","androididmd5":"","imeisha1":"","macsha1":"","idfasha1":"","openudidsha1":"","androididsha1":"","uuidunknow":"","userid":"","iptype":1,"initbidprice":0.0,"adpayment":0.0,"agentrate":0.0,"lomarkrate":0.0,"adxrate":0.0,"title":"","keywords":"","tagid":"","callbackdate":"2016-10-01 06:19:19","channelid":"","mediatype":1}
{"sessionid":"","advertisersid":0,"adorderid":0,"adcreativeid":0,"adplatformproviderid":13,"sdkversion":"未知","adplatformkey":"0b0c1c5523aa40c3a5dcde4402947693","putinmodeltype":0,"requestmode":1,"adprice":0.0,"adppprice":5.0,"requestdate":"2016-10-01 06:19:18","ip":"221.10.135.0","appid":"db55we6weg4hj4","appname":"其他","uuid":"777805177780510","device":"未知","client":1,"osversion":"2.3","density":"1","pw":0,"ph":0,"long":"","lat":"","ispid":1,"ispname":"移动","networkmannerid":1,"networkmannername":"2G","iseffective":0,"isbilling":0,"adspacetype":2,"adspacetypename":"插屏","devicetype":1,"processnode":2,"apptype":4,"district":"未知","paymode":1,"isbid":0,"bidprice":0.0,"winprice":0.0,"iswin":0,"cur":"0","rate":0.0,"cnywinprice":0.0,"imei":"","mac":"","idfa":"","openudid":"","androidid":"","rtbprovince":"","rtbcity":"","rtbdistrict":"","rtbstreet":"","storeurl":"","realip":"221.10.135.0","isqualityapp":0,"bidfloor":0.0,"aw":600,"ah":500,"imeimd5":"","macmd5":"","idfamd5":"","openudidmd5":"","androididmd5":"","imeisha1":"","macsha1":"","idfasha1":"","openudidsha1":"","androididsha1":"","uuidunknow":"","userid":"","iptype":1,"initbidprice":0.0,"adpayment":0.0,"agentrate":0.0,"lomarkrate":0.0,"adxrate":0.0,"title":"","keywords":"","tagid":"","callbackdate":"2016-10-01 06:19:18","channelid":"","mediatype":1}
{"sessionid":"","advertisersid":0,"adorderid":0,"adcreativeid":0,"adplatformproviderid":13,"sdkversion":"未知","adplatformkey":"0b0c1c5523aa40c3a5dcde4402947693","putinmodeltype":0,"requestmode":1,"adprice":0.0,"adppprice":5.0,"requestdate":"2016-10-01 06:18:04","ip":"221.10.135.0","appid":"c1eb4036baa6c944b7cc21407acdcf9e8d9b99b1","appname":"其他","uuid":"340204434020449","device":"未知","client":2,"osversion":"2.0","density":"1","pw":0,"ph":0,"long":"","lat":"","ispid":3,"ispname":"电信","networkmannerid":1,"networkmannername":"2G","iseffective":0,"isbilling":0,"adspacetype":2,"adspacetypename":"插屏","devicetype":1,"processnode":2,"apptype":4,"district":"未知","paymode":1,"isbid":0,"bidprice":0.0,"winprice":0.0,"iswin":0,"cur":"0","rate":0.0,"cnywinprice":0.0,"imei":"","mac":"","idfa":"","openudid":"","androidid":"","rtbprovince":"","rtbcity":"","rtbdistrict":"","rtbstreet":"","storeurl":"","realip":"221.10.135.0","isqualityapp":0,"bidfloor":0.0,"aw":600,"ah":500,"imeimd5":"","macmd5":"","idfamd5":"","openudidmd5":"","androididmd5":"","imeisha1":"","macsha1":"","idfasha1":"","openudidsha1":"","androididsha1":"","uuidunknow":"","userid":"","iptype":1,"initbidprice":0.0,"adpayment":0.0,"agentrate":0.0,"lomarkrate":0.0,"adxrate":0.0,"title":"","keywords":"","tagid":"","callbackdate":"2016-10-01 06:18:04","channelid":"","mediatype":1}
